wxy_MySQL
