Metadata-Version: 1.0
Name: wxy-MySQL
Version: 0.0.5
Summary: MySQL基本增删改查封装
Home-page: https://gitee.com/wang_xing_yuan/wxy-MySQL.git
Author: cooper.wang
Author-email: UNKNOWN
License: MIT
Platform: UNKNOWN
